lihil/__init__.py
lihil/asgi.py
lihil/errors.py
lihil/lihil.py
lihil/local_client.py
lihil/problems.py
lihil/py.typed
lihil/routing.py
lihil/vendors.py
lihil/websocket.py
lihil/config/__init__.py
lihil/config/app_config.py
lihil/config/loader.py
lihil/config/parser.py
lihil/constant/__init__.py
lihil/constant/resp.py
lihil/constant/status.py
lihil/ds/__init__.py
lihil/ds/event.py
lihil/interface/__init__.py
lihil/interface/asgi.py
lihil/interface/marks.py
lihil/interface/problem.py
lihil/interface/struct.py
lihil/oas/__init__.py
lihil/oas/doc_ui.py
lihil/oas/model.py
lihil/oas/schema.py
lihil/plugins/__init__.py
lihil/plugins/bus.py
lihil/plugins/interface.py
lihil/plugins/premier.py
lihil/plugins/auth/__init__.py
lihil/plugins/auth/jwt.py
lihil/plugins/auth/oauth.py
lihil/signature/__init__.py
lihil/signature/params.py
lihil/signature/parser.py
lihil/signature/returns.py
lihil/signature/signature.py
lihil/utils/algorithms.py
lihil/utils/json.py
lihil/utils/sqldbg.py
lihil/utils/string.py
lihil/utils/threading.py
lihil/utils/typing.py
lihil-0.3.30.dist-info/METADATA
lihil-0.3.30.dist-info/WHEEL
lihil-0.3.30.dist-info/licenses/LICENSE
lihil-0.3.30.dist-info/RECORD
