Metadata-Version: 2.4
Name: lihil
Version: 0.3.30
Summary: async python framework offering high level development, low level performance.
Author-email: raceychan <raceychan@gmail.com>
License-File: LICENSE
Classifier: Development Status :: 5 - Production/Stable
Classifier: Intended Audience :: Developers
Classifier: Intended Audience :: Information Technology
Classifier: Intended Audience :: System Administrators
Classifier: Operating System :: OS Independent
Classifier: Programming Language :: Python :: 3 :: Only
Classifier: Programming Language :: Python :: 3.10
Classifier: Programming Language :: Python :: 3.11
Classifier: Programming Language :: Python :: 3.12
Classifier: Programming Language :: Python :: 3.13
Classifier: Topic :: Internet
Classifier: Topic :: Internet :: WWW/HTTP
Classifier: Topic :: Internet :: WWW/HTTP :: HTTP Servers
Classifier: Topic :: Software Development
Classifier: Topic :: Software Development :: Libraries
Classifier: Topic :: Software Development :: Libraries :: Application Frameworks
Classifier: Topic :: Software Development :: Libraries :: Python Modules
Classifier: Typing :: Typed
Requires-Python: >=3.10
Requires-Dist: ididi>=1.6.4
Requires-Dist: msgspec>=0.19.0
Requires-Dist: python-multipart>=0.0.20
Requires-Dist: starlette>=0.48.0
Requires-Dist: typing-extensions>=4.12.2
Provides-Extra: auth
Requires-Dist: pyjwt>=2.10.1; extra == 'auth'
Provides-Extra: standard
Requires-Dist: tomli>=2.2.1; extra == 'standard'
Requires-Dist: uvicorn[standard]>=0.34.0; extra == 'standard'
